.gitignore
.travis.yml
CHANGELOG.rst
LICENSE
MANIFEST.in
README.md
appveyor.yml
setup.cfg
setup.py
data/SPDXJsonExample.json
data/SPDXRdfExample.rdf
data/SPDXSimpleTag.tag
data/SPDXTagExample.tag
data/SPDXXmlExample.xml
data/SPDXYamlExample.yaml
examples/parse_json.py
examples/parse_rdf.py
examples/parse_tv.py
examples/parse_xml.py
examples/parse_yaml.py
examples/pp_rdf.py
examples/pp_tv.py
examples/rdf_to_json.py
examples/rdf_to_tv.py
examples/rdf_to_xml.py
examples/rdf_to_yaml.py
examples/tv_to_json.py
examples/tv_to_rdf.py
examples/tv_to_xml.py
examples/tv_to_yaml.py
examples/write_tv.py
spdx/__init__.py
spdx/annotation.py
spdx/checksum.py
spdx/config.py
spdx/creationinfo.py
spdx/document.py
spdx/element.py
spdx/exceptions.json
spdx/file.py
spdx/licenses.json
spdx/package.py
spdx/relationship.py
spdx/review.py
spdx/snippet.py
spdx/tv_to_rdf.py
spdx/utils.py
spdx/version.py
spdx/parsers/__init__.py
spdx/parsers/builderexceptions.py
spdx/parsers/jsonparser.py
spdx/parsers/jsonyamlxml.py
spdx/parsers/jsonyamlxmlbuilders.py
spdx/parsers/loggers.py
spdx/parsers/rdf.py
spdx/parsers/rdfbuilders.py
spdx/parsers/tagvalue.py
spdx/parsers/tagvaluebuilders.py
spdx/parsers/validations.py
spdx/parsers/xmlparser.py
spdx/parsers/yamlparser.py
spdx/parsers/lexers/__init__.py
spdx/parsers/lexers/tagvalue.py
spdx/writers/__init__.py
spdx/writers/json.py
spdx/writers/jsonyamlxml.py
spdx/writers/rdf.py
spdx/writers/tagvalue.py
spdx/writers/xml.py
spdx/writers/yaml.py
spdx_tools_multiple_packages.egg-info/PKG-INFO
spdx_tools_multiple_packages.egg-info/SOURCES.txt
spdx_tools_multiple_packages.egg-info/dependency_links.txt
spdx_tools_multiple_packages.egg-info/entry_points.txt
spdx_tools_multiple_packages.egg-info/not-zip-safe
spdx_tools_multiple_packages.egg-info/requires.txt
spdx_tools_multiple_packages.egg-info/top_level.txt
tests/__init__.py
tests/test_builder.py
tests/test_config.py
tests/test_conversion.py
tests/test_creationinfo.py
tests/test_document.py
tests/test_jsonyamlxml_parser.py
tests/test_package.py
tests/test_parsers_validation.py
tests/test_rdf_parser.py
tests/test_tag_value_parser.py
tests/testing_utils.LICENSE
tests/testing_utils.py
tests/utils_test.py
tests/data/doc_parse/expected.json
tests/data/doc_parse/spdx-expected.json
tests/data/doc_write/json-simple-plus.json
tests/data/doc_write/json-simple.json
