Metadata-Version: 2.1
Name: spdx-tools-multiple-packages
Version: 0.6.1
Summary: SPDX parser and tools.
Home-page: https://github.com/spdx/tools-python
Author: Ahmed H. Ismail
Author-email: ahm3d.hisham@gmail.com
Maintainer: Philippe Ombredanne, SPDX group at the Linux Foundation and others
Maintainer-email: pombredanne@gmail.com
License: Apache-2.0
Platform: UNKNOWN
Classifier: Intended Audience :: Developers
Classifier: License :: OSI Approved :: Apache Software License
Classifier: Programming Language :: Python :: 2.7
License-File: LICENSE
